{
  "chunk_id": "20160408_Finance_Act_2013_chunk_0027",
  "page_number": 26,
  "document_id": "20160408_Finance_Act_2013",
  "content_blocks": [
    {
      "block_id": "p00026_b001",
      "type": "point",
      "point_number": "৪৩",
      "text": "তৃতীয় তফসিল (ধারা ৭ প্রস্তুত) সম্পূরক শুদ্ধ আরোপযোগ্য পণ্য ও সেবাসমূহ: ২৫.০১ ২৫০১.০০.২০ Salt (other than pure sodium chloride) not in aqueous solution including salt boulder for crushing and salt in bulk ২০; ২৫.০১ ২৫০১.০০.৯৯ অন্যান্য লবণ ২০; ২৫.১৫ ২৫১৫.১১.০০ মার্বেল এবং ট্রেভারটিন (আপাত: আপেক্ষিক পুরুত্ব ২.৫% বা তার বেশী), ক্রুড বা স্কুলভাবে কর্তিত ২০; ২৫.১৫ ২৫১৫.১২.০০ Merely cut, by sawing or otherwise, into blocks or slabs of a rectangular (including square) shape ২০; ২৫.১৫ ২৫১৫.২০.০০ Ecsussine and other calcareous monumental or building stone; alabaster ২০; ২৫.১৬ ২৫১৬.১১.০০ গ্রানাইট (স্কুলভাবে কর্তিত) ২০; ২৫.১৬ ২৫১৬.১২.০০ গ্রানাইট : করাত দ্বারা বা অন্য প্রকারে রুক অথবা চতুর্ভুজ বা বর্গাকার স্লাব হিসাবে কর্তিত ২০; ২৫.১৭ ২৫১৭.১০.৯০ Pebbles, gravel, broken or crushed stone (excl. imported by VAT registered ceramic products manufacturing industries) ২০; ২৫.২৩ ২৫২৩.২১.০০ পোর্টল্যান্ড সিমেন্ট: সাদা, কৃত্রিমভাবে রঙ্গীন করা হটক বা না হটক ২০; ২৫.২৩ ২৫২৩.২৯.০০ অন্যান্য পোর্টল্যান্ড সিমেন্ট ২০; ২৭.১০ ২৭১০.১২.৩৯ অন্যান্য হালকা তৈল ও প্রিপারেশন: অন্যান্য ২০; ২৭.১০ ২৭১০.১২.৫০ অন্যান্য মধ্যম তৈল ও প্রিপারেশন ২০; ২৭.১০ ২৭১০.১২.৬৯ গ্যাস তৈল: অন্যান্য ২০; ২৭.১০ ২৭১০.১৯.১৯ জ্বালানী তৈল: অন্যান্য ২০; ২৭.১০ ২৭১০.১৯.৩৩ আংশিক পরিশোধিত পেট্রোলিয়াম, টপক্রুডসহ ২০; ২৭.১০ ২৭১০.১৯.৩৪ ধীজ (খনিজ) ১০; ২৭.১০ ২৭১০.১৯.৩৯ অন্যান্য ভারী তৈল ও প্রিপারেশন: (ট্রান্সফরমার অয়েল ও হেভি নরম্যাল প্যারাফিন ব্যতীত) ২০; ২৭.১১ ২৭১১.২১.০০ প্রাকৃতিক গ্যাস, গ্যাসীয় অবস্থায় ১০০; ২৮.০৭ ২৮০৭.০০.০০ সালফিউরিক এসিড, ওলিয়াম ২০; ২৯.১৫ ২৯১৫.৭০.৩২ Sodium salt of palmitic acid (soap noodle) imported by other ২০",
      "continues_from_previous": true,
      "continues_to_next": true,
      "stitch_group_id": "point_৪৩",
      "stitching_note": "Continuation of point ৪৩ table content from previous page"
    }
  ],
  "output_carry_forward_state": {
    "status": "open",
    "active_point_number": "৪৩",
    "active_stitch_group_id": "point_৪৩",
    "active_point_summary": "১৯৯১ সনের ২২ নং আইনের তৃতীয় তফসিলের প্রতিস্থাপন।—উক্ত আইনের তৃতীয় তফসিলের পরিবর্তে নিম্নরূপ তৃতীয় তফসিল প্রতিস্থাপিত হইবে, যথা:— তৃতীয় তফসিল (ধারা ৭ প্রস্তুত) সম্পূরক শুদ্ধ আরোপযোগ্য পণ্য ও সেবাসমূহ",
    "numbering_system": "bangla_digits",
    "expected_next_main_point": "৪৪",
    "continuation_hint": "point_৪৩ continues to next page with table content",
    "last_visible_text": "২৯.১৫ ২৯১৫.৭০.৩২ Sodium salt of palmitic acid (soap noodle) imported by other ২০"
  }
}